maya_mcp_server/__init__.py
maya_mcp_server/__main__.py
maya_mcp_server/bootstrap.py
maya_mcp_server/client.py
maya_mcp_server/maya_bootstrap.py
maya_mcp_server/maya_mcp_helper.py
maya_mcp_server/server.py
maya_mcp_server/session_manager.py
maya_mcp_server/types.py
maya_mcp_server/utils.py
maya_mcp_server-0.1.0.dist-info/METADATA
maya_mcp_server-0.1.0.dist-info/WHEEL
maya_mcp_server-0.1.0.dist-info/entry_points.txt
maya_mcp_server-0.1.0.dist-info/RECORD
