Metadata-Version: 2.4
Name: maya-mcp-server
Version: 0.1.0
Summary: MCP server for interacting with Autodesk Maya sessions
Project-URL: Homepage, https://github.com/chadrik/maya-mcp-server
Project-URL: Repository, https://github.com/chadrik/maya-mcp-server
Project-URL: Issues, https://github.com/chadrik/maya-mcp-server/issues
License-Expression: MIT
Keywords: 3d,ai,animation,autodesk,maya,mcp
Classifier: Development Status :: 3 - Alpha
Classifier: Intended Audience :: Developers
Classifier: License :: OSI Approved :: MIT License
Classifier: Programming Language :: Python :: 3
Classifier: Programming Language :: Python :: 3.10
Classifier: Programming Language :: Python :: 3.11
Classifier: Programming Language :: Python :: 3.12
Classifier: Topic :: Multimedia :: Graphics :: 3D Modeling
Requires-Python: >=3.10
Requires-Dist: fastmcp<3.0.0,>=2.0.0
Requires-Dist: psutil
Provides-Extra: dev
Requires-Dist: mypy>=1.0.0; extra == 'dev'
Requires-Dist: pyside6; extra == 'dev'
Requires-Dist: pytest-asyncio>=0.21.0; extra == 'dev'
Requires-Dist: pytest-cov>=4.0.0; extra == 'dev'
Requires-Dist: pytest-mock>=3.0.0; extra == 'dev'
Requires-Dist: pytest>=7.0.0; extra == 'dev'
Requires-Dist: ruff>=0.1.0; extra == 'dev'
Requires-Dist: types-maya-strict; extra == 'dev'
Requires-Dist: types-psutil; extra == 'dev'
Requires-Dist: types-pyside6; extra == 'dev'
